README.md
setup.py
yaval/__init__.py
yaval/misc.py
yaval/plugin.py
yaval/plugin_matplotlib.py
yaval/plugin_vispy.py
yaval/qt.py
yaval/values.py
yaval/visualizer.py
yaval.egg-info/PKG-INFO
yaval.egg-info/SOURCES.txt
yaval.egg-info/dependency_links.txt
yaval.egg-info/requires.txt
yaval.egg-info/top_level.txt